acsoo/__init__.py
acsoo/_list_depends
acsoo/addons.py
acsoo/cache.py
acsoo/checklog.py
acsoo/config.py
acsoo/freeze.py
acsoo/main.py
acsoo/manifest.py
acsoo/pr_status.py
acsoo/release.py
acsoo/tag.py
acsoo/tag_requirements.py
acsoo/tools.py
acsoo/wheel.py
acsoo-3.4.1.dist-info/LICENSE
acsoo-3.4.1.dist-info/METADATA
acsoo-3.4.1.dist-info/WHEEL
acsoo-3.4.1.dist-info/entry_points.txt
acsoo-3.4.1.dist-info/top_level.txt
acsoo-3.4.1.dist-info/RECORD
