Metadata-Version: 2.1
Name: acsoo
Version: 3.4.1
Summary: Acsone Odoo Dev Tools
License: GPLv3+
Classifier: Development Status :: 5 - Production/Stable
Classifier: Intended Audience :: Developers
Classifier: License :: OSI Approved :: GNU General Public License v3 or later (GPLv3+)
Classifier: Operating System :: POSIX
Classifier: Programming Language :: Python :: 3.6
Classifier: Programming Language :: Python :: 3.7
Classifier: Programming Language :: Python :: 3.8
Classifier: Framework :: Odoo
Requires-Python: >=3.6
License-File: LICENSE
Requires-Dist: appdirs
Requires-Dist: click
Requires-Dist: colorama
Requires-Dist: configparser
Requires-Dist: pip >=9.0.1
Requires-Dist: setuptools
Requires-Dist: wheel >=0.29
Requires-Dist: httpx
Requires-Dist: tomli
